github_tools/__init__.py
github_tools/github_tools.py
github_tools_a-0.0.1.dist-info/METADATA
github_tools_a-0.0.1.dist-info/WHEEL
github_tools_a-0.0.1.dist-info/top_level.txt
github_tools_a-0.0.1.dist-info/RECORD
