Metadata-Version: 2.1
Name: github-tools-a
Version: 0.0.1
Summary: A tool to perform certain GitHub tasks.
License: The MIT License (MIT)
Requires-Dist: requests
